EasyVectorsPy/__init__.py
EasyVectorsPy-0.0.5.dist-info/METADATA
EasyVectorsPy-0.0.5.dist-info/WHEEL
EasyVectorsPy-0.0.5.dist-info/top_level.txt
EasyVectorsPy-0.0.5.dist-info/RECORD
