Metadata-Version: 2.1
Name: EasyVectorsPy
Version: 0.0.5
Summary: library that helps when working with coordinates like(Pillow, Pygame)
Home-page: https://github.com/nellle/EasyVectorsPy
Author: Nellle
License: UNKNOWN
Project-URL: Bug Tracker, https://github.com/nellle/EasyVectorsPy/issues
Project-URL: Wiki, https://github.com/nellle/EasyVectorsPy/wiki
Keywords: python,vectors,easy,easy vectors
Platform: UNKNOWN
Classifier: Development Status :: 1 - Planning
Classifier: Intended Audience :: Developers
Classifier: Programming Language :: Python :: 3.8
Classifier: Operating System :: Unix
Classifier: Operating System :: MacOS :: MacOS X
Classifier: Operating System :: Microsoft :: Windows
